ir_ldr/__init__.py
ir_ldr/private.py
ir_ldr/file/chi_table.csv
ir_ldr/file/example_spectra/dwarf/order43.txt
ir_ldr/file/example_spectra/dwarf/order44.txt
ir_ldr/file/example_spectra/dwarf/order45.txt
ir_ldr/file/example_spectra/dwarf/order46.txt
ir_ldr/file/example_spectra/dwarf/order47.txt
ir_ldr/file/example_spectra/dwarf/order48.txt
ir_ldr/file/example_spectra/dwarf/order52.txt
ir_ldr/file/example_spectra/dwarf/order53.txt
ir_ldr/file/example_spectra/dwarf/order54.txt
ir_ldr/file/example_spectra/dwarf/order55.txt
ir_ldr/file/example_spectra/dwarf/order56.txt
ir_ldr/file/example_spectra/dwarf/order57.txt
ir_ldr/file/h-ldr/lineratio_giant.csv
ir_ldr/file/yj-ldr/lineratio_all_dwarf_j20a.csv
ir_ldr/file/yj-ldr/lineratio_all_giant_t18.csv
ir_ldr/file/yj-ldr/lineratio_all_spg_j20a.csv
ir_ldr_mingjie-0.1.4.dist-info/LICENSE
ir_ldr_mingjie-0.1.4.dist-info/METADATA
ir_ldr_mingjie-0.1.4.dist-info/WHEEL
ir_ldr_mingjie-0.1.4.dist-info/top_level.txt
ir_ldr_mingjie-0.1.4.dist-info/RECORD
