Metadata-Version: 2.1
Name: ir-ldr-mingjie
Version: 0.1.4
Summary: The python package to deal with infrared LDR and Teff.
Home-page: https://github.com/MingjieJian/ir_ldr
Author: Mingjie Jian
Author-email: ssaajianmingjie@gmail.com
License: UNKNOWN
Platform: UNKNOWN
Classifier: Programming Language :: Python :: 3
Classifier: License :: OSI Approved :: MIT License
Classifier: Framework :: IPython
Classifier: Operating System :: OS Independent
Classifier: Development Status :: 3 - Alpha
Classifier: Topic :: Scientific/Engineering :: Astronomy
Requires-Dist: numpy (>=1.17.0)
Requires-Dist: pandas (>=0.20.0)
Requires-Dist: matplotlib (>=3.0.0)
Requires-Dist: scipy (>=1.0.0)
